flake8_ls/__init__.py
flake8_ls-1.8.dist-info/LICENSE
flake8_ls-1.8.dist-info/METADATA
flake8_ls-1.8.dist-info/WHEEL
flake8_ls-1.8.dist-info/entry_points.txt
flake8_ls-1.8.dist-info/top_level.txt
flake8_ls-1.8.dist-info/RECORD
